__init__.py
expressoptionchain/__init__.py
expressoptionchain/exceptions.py
expressoptionchain/helper.py
expressoptionchain/instrument_manager.py
expressoptionchain/kite_connector.py
expressoptionchain/option_chain.py
expressoptionchain/option_stream.py
expressoptionchain/redis_helper.py
expressoptionchain/examples/__init__.py
expressoptionchain/examples/advanced_usage.py
expressoptionchain/examples/fetch_option_chain.py
expressoptionchain/examples/runner.py
expressoptionchain/examples/start_option_chain_process.py
express_option_chain-1.0.6.dist-info/LICENSE
express_option_chain-1.0.6.dist-info/METADATA
express_option_chain-1.0.6.dist-info/WHEEL
express_option_chain-1.0.6.dist-info/top_level.txt
express_option_chain-1.0.6.dist-info/RECORD
