Metadata-Version: 2.1
Name: express-option-chain
Version: 1.0.6
Summary: This library utilizes Kite Connect APIs to fetch the option chain of all the derivatives traded in the Indian stock market.
Author-email: Prajwal Ramakrishna <prajwaldr9@gmail.com>
License: Copyright (c) 2023, Prajwal Ramakrishna.
Project-URL: Homepage, https://github.com/pramakrishn/express-option-chain
Keywords: option-chain,kite-option-chain,nse-option-chain,nse-options,india-equity-options
Classifier: License :: OSI Approved :: MIT License
Classifier: Programming Language :: Python
Classifier: Programming Language :: Python :: 3
Requires-Python: >=3.9
License-File: LICENSE
Requires-Dist: requests
Requires-Dist: kiteconnect
Requires-Dist: redis
